{"JMEzqEwdalCKVJvitEC+/A==":"mbr-1646x1097.jpg","JuiH1kuACDyLzriuNA7dvA==":"white%20brown%20modern%20coffee%20shop%20logo-121x121.png","juJdhRYecydt9Lve8Lc23w==":"mbr-1920x1258.jpeg","nbQzhIRoqXiRlz6V/F8wiA==":"mbr-1920x1280.jpg","796MY6YqZ0ssNeGcHSplww==":"mbr-1920x1330.jpg","YawxdoRxJwf4rPo1dPEj6w==":"mbr-609x343.jpeg","WxH7z5r/1nEdhpLkFd4cWg==":"iced%20latte%20with%20swirl-609x406.jpeg","xdMrrH8/u1mXsZl25faF7Q==":"5f6d2413c43f9-609x407.jpeg","Reym5WY8QtliIOoZYZ/zOQ==":"milkshake-609x405.jpeg","3VNR7gDi3rwykWvgY+vnAA==":"mbr-1920x1002.jpg","E36fKM4CFdbD3kUnryB1Cw==":"pngtree-brown-coffee-simple-background-image-501628-289x405.jpeg","RDtinkipq6mkGGDM/dzbpQ==":"pngtree-brown-coffee-simple-background-image-501629-289x405.jpeg","j/Ab4CvpYV5Z9QqQvvFMig==":"istockphoto-1179275966-612x435.jpg","s3E07sfrxqz/EokG8UHltg==":"v926-adj-031-f-x-675x1200.jpg","GYcDSuLcpV+3meOZnOa5Mw==":"v926-adj-031-f-x-675x1200.jpeg","5TK9QheI/00lMEwrza3+FQ==":"istockphoto-1364440645-612x392.jpg","+s5oqnqzPzHzSq1+ufU8VA==":"ecc832f8a484f4d3f9ff6870ed95a5cf-564x1002.jpg","EAWHSWv8bkC4v5BsdYwnag==":"a746e73b00b26d295e32f62ba77fd74e-564x789.jpeg","re5qWeBubsYfwevB3m94aw==":"9562bf9d794f3d8d59f7e3fde205fdc4-564x564.jpg","1qzWPGA/4DlyAI3iSRx/hw==":"image-asset-600x898.jpg","WCvO/ykxuRBemup9YuvoCg==":"blueberry-scones-9-609x913.jpg","QnCPstgyRzMy49bPDuA8Ng==":"bakery-style-chocolate-chip-cookies-1-609x914.jpg","CYQ0U4vpO3O/hBoo4U1tBg==":"blueberry-cheesecake-609x609.jpg"}